{
  "project_info": {
    "project_number": "574392477853",
    "firebase_url": "https://ex-books-223e9.firebaseio.com",
    "project_id": "ex-books-223e9",
    "storage_bucket": "ex-books-223e9.appspot.com"
  },
  "client": [
    {
      "client_info": {
        "mobilesdk_app_id": "1:574392477853:android:9ae072995ab317ec768c74",
        "android_client_info": {
          "package_name": "com.example.admin_gp"
        }
      },
      "oauth_client": [
        {
          "client_id": "574392477853-lokp075q1qqael1m5si3nuahn55svafq.apps.googleusercontent.com",
          "client_type": 3
        }
      ],
      "api_key": [
        {
          "current_key": "AIzaSyAIPBlLbj5blnPkmurwhyyZRpbPhWbY-6U"
        }
      ],
      "services": {
        "appinvite_service": {
          "other_platform_oauth_client": [
            {
              "client_id": "574392477853-lokp075q1qqael1m5si3nuahn55svafq.apps.googleusercontent.com",
              "client_type": 3
            }
          ]
        }
      }
    },
    {
      "client_info": {
        "mobilesdk_app_id": "1:574392477853:android:3480985bdeb1bcb0768c74",
        "android_client_info": {
          "package_name": "com.example.ex_books"
        }
      },
      "oauth_client": [
        {
          "client_id": "574392477853-v9idsbmikube6hru70jtetlarmsrm5md.apps.googleusercontent.com",
          "client_type": 1,
          "android_info": {
            "package_name": "com.example.ex_books",
            "certificate_hash": "8e577f10551192118fd05b58f6f9254786e0e498"
          }
        },
        {
          "client_id": "574392477853-lokp075q1qqael1m5si3nuahn55svafq.apps.googleusercontent.com",
          "client_type": 3
        }
      ],
      "api_key": [
        {
          "current_key": "AIzaSyAIPBlLbj5blnPkmurwhyyZRpbPhWbY-6U"
        }
      ],
      "services": {
        "appinvite_service": {
          "other_platform_oauth_client": [
            {
              "client_id": "574392477853-lokp075q1qqael1m5si3nuahn55svafq.apps.googleusercontent.com",
              "client_type": 3
            }
          ]
        }
      }
    },
    {
      "client_info": {
        "mobilesdk_app_id": "1:574392477853:android:ad2968277baa0c0e768c74",
        "android_client_info": {
          "package_name": "com.exbooks.admin_gp"
        }
      },
      "oauth_client": [
        {
          "client_id": "574392477853-lokp075q1qqael1m5si3nuahn55svafq.apps.googleusercontent.com",
          "client_type": 3
        }
      ],
      "api_key": [
        {
          "current_key": "AIzaSyAIPBlLbj5blnPkmurwhyyZRpbPhWbY-6U"
        }
      ],
      "services": {
        "appinvite_service": {
          "other_platform_oauth_client": [
            {
              "client_id": "574392477853-lokp075q1qqael1m5si3nuahn55svafq.apps.googleusercontent.com",
              "client_type": 3
            }
          ]
        }
      }
    }
  ],
  "configuration_version": "1"
}